rpycocotools-stubs/__init__.pyi
rpycocotools-stubs/anns.pyi
rpycocotools-stubs/mask.pyi
rpycocotools-stubs/py.typed
rpycocotools_stubs-0.0.7.dist-info/METADATA
rpycocotools_stubs-0.0.7.dist-info/WHEEL
rpycocotools_stubs-0.0.7.dist-info/licenses/LICENSE
rpycocotools_stubs-0.0.7.dist-info/RECORD
